ezinputs/__init__.py
ezinputs/ezinputs.py
ezinputs-1.0.1.dist-info/METADATA
ezinputs-1.0.1.dist-info/WHEEL
ezinputs-1.0.1.dist-info/top_level.txt
ezinputs-1.0.1.dist-info/RECORD
