Metadata-Version: 2.1
Name: ezinputs
Version: 1.0.1
Summary: Easily manage getting user inputs for all data types
Home-page: UNKNOWN
Author: Will Johnson
License: MIT
Platform: UNKNOWN
